snapper/__init__.py
snapper/cli.py
snapper/utils.py
dr_snapper-0.3.5.dist-info/LICENSE
dr_snapper-0.3.5.dist-info/METADATA
dr_snapper-0.3.5.dist-info/WHEEL
dr_snapper-0.3.5.dist-info/entry_points.txt
dr_snapper-0.3.5.dist-info/RECORD
