Metadata-Version: 2.1
Name: dr-snapper
Version: 0.3.5
Summary: Create a new timeline 'snapshot' to revert to when trying out risky ideas in DaVinci Resolve
Home-page: https://github.com/in03/snapper
License: MIT
Keywords: DaVinci Resolve,Scripting,Backups,CLI
Author: Caleb Trevatt
Author-email: in03@users.noreply.github.com
Requires-Python: >=3.10.0,<3.12.0
Classifier: License :: OSI Approved :: MIT License
Classifier: Operating System :: OS Independent
Classifier: Programming Language :: Python :: 3
Classifier: Programming Language :: Python :: 3.10
Classifier: Programming Language :: Python :: 3.11
Classifier: Programming Language :: Python :: 3
Requires-Dist: natsort (>=8.1.0,<9.0.0)
Requires-Dist: pydavinci-18 (>=0.3.1,<0.4.0)
Requires-Dist: pyfiglet (>=0.8.post1,<0.9)
Requires-Dist: rich (>=12.0.1,<13.0.0)
Requires-Dist: typer (>=0.4.0,<0.5.0)
Project-URL: Repository, https://github.com/in03/snapper
